pygam2/__init__.py
pygam2/callbacks.py
pygam2/core.py
pygam2/distributions.py
pygam2/links.py
pygam2/penalties.py
pygam2/pygam.py
pygam2/terms.py
pygam2/utils.py
pygam2/datasets/__init__.py
pygam2/datasets/blood1.csv
pygam2/datasets/cake.csv
pygam2/datasets/chicago.csv
pygam2/datasets/coal.csv
pygam2/datasets/default.csv
pygam2/datasets/faithful.csv
pygam2/datasets/head_circumference.csv
pygam2/datasets/hepatitis_A_bulgaria.csv
pygam2/datasets/load_datasets.py
pygam2/datasets/mcycle.csv
pygam2/datasets/trees.csv
pygam2/datasets/wage.csv
pygam2/tests/__init__.py
pygam2/tests/conftest.py
pygam2/tests/test_GAM_methods.py
pygam2/tests/test_GAM_params.py
pygam2/tests/test_GAMs.py
pygam2/tests/test_core.py
pygam2/tests/test_datasets.py
pygam2/tests/test_gridsearch.py
pygam2/tests/test_partial_dependence.py
pygam2/tests/test_penalties.py
pygam2/tests/test_terms.py
pygam2/tests/test_utils.py
pygam2-0.9.1.dist-info/LICENSE
pygam2-0.9.1.dist-info/WHEEL
pygam2-0.9.1.dist-info/METADATA
pygam2-0.9.1.dist-info/RECORD
